README.rst
setup.cfg
setup.py
hexagonit/__init__.py
hexagonit.portletroles.egg-info/PKG-INFO
hexagonit.portletroles.egg-info/SOURCES.txt
hexagonit.portletroles.egg-info/dependency_links.txt
hexagonit.portletroles.egg-info/entry_points.txt
hexagonit.portletroles.egg-info/namespace_packages.txt
hexagonit.portletroles.egg-info/not-zip-safe
hexagonit.portletroles.egg-info/requires.txt
hexagonit.portletroles.egg-info/top_level.txt
hexagonit/portletroles/__init__.py
hexagonit/portletroles/configure.zcml
hexagonit/portletroles/overrides.zcml
hexagonit/portletroles/browser/__init__.py
hexagonit/portletroles/browser/interfaces.py
hexagonit/portletroles/docs/CONTRIBUTORS.rst
hexagonit/portletroles/docs/HISTORY.rst
hexagonit/portletroles/docs/INSTALL.rst
hexagonit/portletroles/docs/LICENSE.rst
hexagonit/portletroles/docs/Makefile
hexagonit/portletroles/docs/README.rst
hexagonit/portletroles/docs/conf.py
hexagonit/portletroles/docs/index.rst
hexagonit/portletroles/profiles/default/browserlayer.xml
hexagonit/portletroles/profiles/default/metadata.xml
hexagonit/portletroles/tests/__init__.py
hexagonit/portletroles/tests/base.py
hexagonit/portletroles/tests/test_functional.py
hexagonit/portletroles/tests/test_setup.py
hexagonit/portletroles/tests/functional/browser.txt
hexagonit/portletroles/tests/rolemap/__init__.py
hexagonit/portletroles/tests/rolemap/configure.zcml
hexagonit/portletroles/tests/rolemap/profiles/default/portlets.xml
hexagonit/portletroles/tests/rolemap/profiles/default/rolemap.xml