Metadata-Version: 1.0
Name: hexagonit.portletroles
Version: 1.0
Summary: Provides roles for adding each portlets.
Home-page: http://www.hexagonit.fi
Author: Hexagon IT
Author-email: oss@hexagonit.fi
License: BSD
Platform: UNKNOWN
Classifier: Framework :: Plone
Classifier: Framework :: Plone :: 4.1
Classifier: Framework :: Plone :: 4.2
Classifier: Framework :: Plone :: 4.3
Classifier: Programming Language :: Python
